gencodegenes/__init__.py
gencodegenes/gencode.cp310-win_amd64.pyd
gencodegenes/gencode.cpp
gencodegenes/gencode.pyx
gencodegenes/transcript.cp310-win_amd64.pyd
gencodegenes/transcript.cpp
gencodegenes/transcript.pxd
gencodegenes/transcript.pyx
gencodegenes/tx.cpp
gencodegenes/tx.h
gencodegenes-1.1.6.dist-info/licenses/LICENSE.txt
gencodegenes-1.1.6.dist-info/METADATA
gencodegenes-1.1.6.dist-info/WHEEL
gencodegenes-1.1.6.dist-info/top_level.txt
gencodegenes-1.1.6.dist-info/RECORD
