Metadata-Version: 2.1
Name: gencodegenes
Version: 1.1.6
Summary: Package to load genes from GENCODE GTF files
Author-email: Jeremy McRae <jeremy.mcrae@gmail.com>
Project-URL: homepage, https://github.com/jeremymcrae/gencodegenes
Classifier: License :: OSI Approved :: MIT License
Classifier: Development Status :: 4 - Beta
Classifier: Topic :: Scientific/Engineering :: Bio-Informatics
Requires-Python: >=3.8
License-File: LICENSE.txt
Requires-Dist: pyfaidx>=0.5.8
